bqskit/__init__.py
bqskit/_logging.py
bqskit/_version.py
bqskit/compiler/__init__.py
bqskit/compiler/basepass.py
bqskit/compiler/compile.py
bqskit/compiler/compiler.py
bqskit/compiler/gateset.py
bqskit/compiler/machine.py
bqskit/compiler/passdata.py
bqskit/compiler/registry.py
bqskit/compiler/status.py
bqskit/compiler/task.py
bqskit/compiler/workflow.py
bqskit/exec/__init__.py
bqskit/exec/results.py
bqskit/exec/runner.py
bqskit/exec/runners/__init__.py
bqskit/exec/runners/ibmq.py
bqskit/exec/runners/quest.py
bqskit/exec/runners/sim.py
bqskit/ext/__init__.py
bqskit/ext/quantinuum.py
bqskit/ext/rigetti.py
bqskit/ext/supermarq.py
bqskit/ext/cirq/__init__.py
bqskit/ext/cirq/models.py
bqskit/ext/cirq/translate.py
bqskit/ext/pytket/__init__.py
bqskit/ext/pytket/translate.py
bqskit/ext/qiskit/__init__.py
bqskit/ext/qiskit/models.py
bqskit/ext/qiskit/translate.py
bqskit/ext/qutip/__init__.py
bqskit/ext/qutip/translate.py
bqskit/ir/__init__.py
bqskit/ir/circuit.py
bqskit/ir/gate.py
bqskit/ir/interval.py
bqskit/ir/iterator.py
bqskit/ir/location.py
bqskit/ir/operation.py
bqskit/ir/point.py
bqskit/ir/region.py
bqskit/ir/structure.py
bqskit/ir/gates/__init__.py
bqskit/ir/gates/barrier.py
bqskit/ir/gates/circuitgate.py
bqskit/ir/gates/composedgate.py
bqskit/ir/gates/constantgate.py
bqskit/ir/gates/generalgate.py
bqskit/ir/gates/measure.py
bqskit/ir/gates/qubitgate.py
bqskit/ir/gates/quditgate.py
bqskit/ir/gates/qutritgate.py
bqskit/ir/gates/reset.py
bqskit/ir/gates/composed/__init__.py
bqskit/ir/gates/composed/controlled.py
bqskit/ir/gates/composed/daggergate.py
bqskit/ir/gates/composed/embedded.py
bqskit/ir/gates/composed/frozenparam.py
bqskit/ir/gates/composed/powergate.py
bqskit/ir/gates/composed/tagged.py
bqskit/ir/gates/composed/vlg.py
bqskit/ir/gates/constant/__init__.py
bqskit/ir/gates/constant/b.py
bqskit/ir/gates/constant/ccx.py
bqskit/ir/gates/constant/ch.py
bqskit/ir/gates/constant/clock.py
bqskit/ir/gates/constant/cpi.py
bqskit/ir/gates/constant/cs.py
bqskit-1.2.0.dist-info/LICENSE
bqskit-1.2.0.dist-info/METADATA
bqskit-1.2.0.dist-info/WHEEL
bqskit-1.2.0.dist-info/entry_points.txt
bqskit-1.2.0.dist-info/top_level.txt
bqskit-1.2.0.dist-info/RECORD
