Metadata-Version: 2.1
Name: bqskit
Version: 1.2.0
Summary: Berkeley Quantum Synthesis Toolkit
Home-page: https://github.com/BQSKit/bqskit
Author: LBNL - BQSKit developers
Author-email: edyounis@lbl.gov
License: BSD 3-Clause License
Project-URL: Bug Tracker, https://github.com/BQSKit/bqskit/issues
Project-URL: Source Code, https://github.com/BQSKit/bqskit
Project-URL: Documentation, https://bqskit.readthedocs.io/en/latest
Keywords: berkeley,quantum,synthesis,toolkit,partitioning
Classifier: Development Status :: 5 - Production/Stable
Classifier: Environment :: Console
Classifier: Intended Audience :: Developers
Classifier: Intended Audience :: Education
Classifier: Intended Audience :: Science/Research
Classifier: License :: OSI Approved :: BSD License
Classifier: Operating System :: MacOS
Classifier: Operating System :: Microsoft :: Windows
Classifier: Operating System :: POSIX :: Linux
Classifier: Programming Language :: Python :: 3 :: Only
Classifier: Programming Language :: Python :: 3.8
Classifier: Programming Language :: Python :: 3.9
Classifier: Programming Language :: Python :: 3.10
Classifier: Programming Language :: Python :: 3.11
Classifier: Programming Language :: Python :: 3.12
Classifier: Topic :: Scientific/Engineering
Classifier: Topic :: Scientific/Engineering :: Mathematics
Classifier: Topic :: Scientific/Engineering :: Physics
Classifier: Topic :: Software Development :: Compilers
Classifier: Typing :: Typed
Requires-Python: >=3.8, <4
License-File: LICENSE
Requires-Dist: bqskitrs>=0.4.1
Requires-Dist: lark
Requires-Dist: numpy>=1.22.0
Requires-Dist: scipy>=1.8.0
Requires-Dist: typing-extensions>=4.0.0
Requires-Dist: dill>=0.3.8
Provides-Extra: dev
Requires-Dist: hypothesis[zoneinfo]; extra == "dev"
Requires-Dist: mypy; extra == "dev"
Requires-Dist: pre-commit; extra == "dev"
Requires-Dist: psutil; extra == "dev"
Requires-Dist: pytest; extra == "dev"
Requires-Dist: tox; extra == "dev"
